proteinko/__init__.py
proteinko/amino_acid_data.csv
proteinko/protein_dist.py
proteinko/schemas.py
proteinko/utils.py
proteinko-5.0.dist-info/LICENSE
proteinko-5.0.dist-info/METADATA
proteinko-5.0.dist-info/WHEEL
proteinko-5.0.dist-info/top_level.txt
proteinko-5.0.dist-info/RECORD
