Metadata-Version: 2.1
Name: proteinko
Version: 5.0
Summary: Encode protein sequence as a distribution of its physicochemical properties
Home-page: https://github.com/stefs304/proteinko
Author: Stefan Stojanovic
Author-email: stefs304@gmail.com
License: UNKNOWN
Platform: UNKNOWN
Classifier: Programming Language :: Python :: 3.8
Classifier: Programming Language :: Python :: 3.7
Classifier: Programming Language :: Python :: 3.6
Classifier: Programming Language :: Python :: 3.5
Classifier: License :: OSI Approved :: MIT License
Classifier: Intended Audience :: Science/Research
Classifier: Intended Audience :: Healthcare Industry
Classifier: Topic :: Scientific/Engineering :: Bio-Informatics
Classifier: Topic :: Scientific/Engineering :: Chemistry
Requires-Dist: numpy
